olchiki/__init__.py
olchiki-0.0.1.dist-info/METADATA
olchiki-0.0.1.dist-info/WHEEL
olchiki-0.0.1.dist-info/top_level.txt
olchiki-0.0.1.dist-info/RECORD
